hellostreamlit_wc/__init__.py
hellostreamlit_wc/hello.py
hellostreamlit_wc-0.1.0.dist-info/METADATA
hellostreamlit_wc-0.1.0.dist-info/WHEEL
hellostreamlit_wc-0.1.0.dist-info/top_level.txt
hellostreamlit_wc-0.1.0.dist-info/RECORD
