Metadata-Version: 2.1
Name: hellostreamlit_wc
Version: 0.1.0
Summary: Practice streamlit
Author-email: whitecapella1 <whitecapella@naver.com>
License: MIT
Requires-Python: ==3.11.*
Requires-Dist: streamlit >=1.36.0
